cyberwatch_api.py
cbw_cli/__init__.py
cbw_cli/cyberwatch_cli.py
cbw_cli/bin/__init__.py
cbw_cli/bin/os.py
cbw_cli/bin/airgap/__init__.py
cbw_cli/bin/airgap/download_compliance_scripts.py
cbw_cli/bin/airgap/download_scripts.py
cbw_cli/bin/airgap/upload_compliance_scripts.py
cbw_cli/bin/airgap/upload_scripts.py
cyberwatch_api-1.0.0.dist-info/licenses/LICENSE
examples/add_windows_os_to_rules_of_repository.py
examples/change_asset_group_from_hostname.py
examples/create_agentless_ssh_ed25519_key.py
examples/create_agentless_ssh_password.py
examples/create_agentless_ssh_rsa_key.py
examples/create_agentless_winrm_negociate.py
examples/cve_code_to_cvss.py
examples/cve_resolution_time.py
examples/hostname_to_cvss_vector.py
examples/mean_cve_resolution_time_per_year.py
examples/remove_assets_based_on_last_communication.py
examples/remove_duplicated_assets.py
examples/retrieve_assets_with_kb_patch_available.py
examples/retrieve_high_priorities_cve.py
examples/retrieve_priorized_cve_during_the_past_x_days.py
examples/retrieve_top-10-cve_kb-to-patch_os-obsolete_cve-discovered_cve-patched.py
examples/nessus_integration/cbw_helper.py
examples/nessus_integration/main.py
examples/two_instance_sync/sync_assets.py
cyberwatch_api-1.0.0.dist-info/METADATA
cyberwatch_api-1.0.0.dist-info/WHEEL
cyberwatch_api-1.0.0.dist-info/entry_points.txt
cyberwatch_api-1.0.0.dist-info/top_level.txt
cyberwatch_api-1.0.0.dist-info/RECORD
