Metadata-Version: 2.4
Name: cyberwatch_api
Version: 1.0.0
Summary: Python Api client for the Cyberwatch software
Author: CyberWatch SAS
License-Expression: MIT
Requires-Python: >=3.6
License-File: LICENSE
Requires-Dist: requests>=2.20.1
Requires-Dist: chardet
Dynamic: license-file
